kringle/__about__.py
kringle/__init__.py
kringle/core.py
kringle-0.2.1.dist-info/METADATA
kringle-0.2.1.dist-info/WHEEL
kringle-0.2.1.dist-info/entry_points.txt
kringle-0.2.1.dist-info/licenses/LICENSE.txt
kringle-0.2.1.dist-info/RECORD
