Metadata-Version: 2.1
Name: kringle
Version: 0.2.1
Summary: A solution manager for Advent of Code
Project-URL: Documentation, https://github.com/stephenlutes/kringle#readme
Project-URL: Issues, https://github.com/stephenlutes/kringle/issues
Project-URL: Source, https://github.com/stephenlutes/kringle
Author: Stephen Lutes
License-Expression: MIT
License-File: LICENSE.txt
Classifier: Development Status :: 4 - Beta
Classifier: Programming Language :: Python
Classifier: Programming Language :: Python :: 3.8
Classifier: Programming Language :: Python :: 3.9
Classifier: Programming Language :: Python :: 3.10
Classifier: Programming Language :: Python :: 3.11
Classifier: Programming Language :: Python :: 3.12
Classifier: Programming Language :: Python :: Implementation :: CPython
Classifier: Programming Language :: Python :: Implementation :: PyPy
Requires-Python: >=3.8
